Workbook
Name anos: SIMULADOR!$D$12
Name Aporte: SIMULADOR!$D$11
Name cenario10: SIMULADOR!$C$20
Name cenario2: SIMULADOR!$C$18
Name cenario20: SIMULADOR!$C$21
Name cenario30: SIMULADOR!$C$22
Name cenario5: SIMULADOR!$C$19
Name patrimonio: SIMULADOR!$D$14
Name Perc_Sal: SIMULADOR!$D$8
Name rend_Cart: SIMULADOR!$D$7
Name Salario: SIMULADOR!$D$6
Name Tx_Mensal: SIMULADOR!$D$13

Sheet SIMULADOR
B5: CONFIGURAÇÕES
B6: Qual Seu Salario Mensal? | D6: 12000
B7: Rendimento Carteira | D7: 0.01
B8: Qual % do seu salario voce que investir? | D8: 0.01
B10: INVESTIMENTO MENSAL
B11: Quanto Investir por Mês ? | D11: =D6*D8 -> 120
B12: Por Quantos Anos? | D12: 1
B13: Taxa de Rendimento Mensal? | D13: 0.01079
B14: Patrimonio Acumulado? | D14: =FV(Tx_Mensal,anos*12,Aporte*-1) -> 1528.6063
B15: Dividendos Mensais? | D15: =patrimonio*rend_Cart -> 15.286063
B17: Cenarios | D17: Dividendos
A18: 2 | B18: Quanto em 2 Anos? | C18: =FV(Tx_Mensal,$A18*12,Aporte*-1) -> 3267.3153 | D18: =cenario2*rend_Cart -> 32.673153
A19: 5 | B19: Quanto em 5 Anos? | C19: =FV(Tx_Mensal,$A19*12,Aporte*-1) -> 10053.23 | D19: =cenario5*Tx_Mensal -> 108.47435
A20: 10 | B20: Quanto em 10 Anos? | C20: =FV(Tx_Mensal,$A20*12,Aporte*-1) -> 29194.106 | D20: =cenario10*Tx_Mensal -> 315.0044
A21: 20 | B21: Quanto em 20 Anos? | C21: =FV(Tx_Mensal,$A21*12,Aporte*-1) -> 135023.81 | D21: =cenario20*Tx_Mensal -> 1456.9069
A22: 30 | B22: Quanto em 30 Anos? | C22: =FV(Tx_Mensal,$A22*12,Aporte*-1) -> 518660.36 | D22: =cenario30*Tx_Mensal -> 5596.3453
B25: Perfil | C25: CONSERVADOR
B26: VALOR A SER INVESTIDO POR MÊS | C26: =Aporte -> 120
B28: TIPO DE FII | C28: % Sugerido | D28: Valores
B29: PAPEL | C29: =VLOOKUP($C$25&"-"&B29,APOIO!A4:D21,4,FALSE) -> 0.3 | D29: =$C$26*C29 -> 36
B30: TIJOLO | C30: =VLOOKUP($C$25&"-"&B30,APOIO!A5:D22,4,FALSE) -> 0.5 | D30: =$C$26*C30 -> 60
B31: HIBRIDOS | C31: =VLOOKUP($C$25&"-"&B31,APOIO!A6:D23,4,FALSE) -> 0.1 | D31: =$C$26*C31 -> 12
B32: FOFs | C32: =VLOOKUP($C$25&"-"&B32,APOIO!A7:D24,4,FALSE) -> 0.1 | D32: =$C$26*C32 -> 12
B33: DESENVOLVIMENTO | C33: =VLOOKUP($C$25&"-"&B33,APOIO!A8:D25,4,FALSE) -> 0 | D33: =$C$26*C33 -> 0
B34: HOTELARIAS | C34: =VLOOKUP($C$25&"-"&B34,APOIO!A9:D26,4,FALSE) -> 0 | D34: =$C$26*C34 -> 0
B35: TOTAL | D35: =SUM(D29:D34) -> 120

Sheet APOIO
A3: CHAVE | B3: PERFIL | C3: TIPO DE FII | D3: %
A4: =B4&"-"&C4 -> AGRESSIVO-PAPEL | B4: AGRESSIVO | C4: PAPEL | D4: 0.5
A5: =B5&"-"&C5 -> AGRESSIVO-TIJOLO | B5: AGRESSIVO | C5: TIJOLO | D5: 0.1
A6: =B6&"-"&C6 -> AGRESSIVO-HIBRIDOS | B6: AGRESSIVO | C6: HIBRIDOS | D6: 0.05
A7: =B7&"-"&C7 -> AGRESSIVO-FOFs | B7: AGRESSIVO | C7: FOFs | D7: 0.05
A8: =B8&"-"&C8 -> AGRESSIVO-DESENVOLVIMENTO | B8: AGRESSIVO | C8: DESENVOLVIMENTO | D8: 0.2
A9: =B9&"-"&C9 -> AGRESSIVO-HOTELARIAS | B9: AGRESSIVO | C9: HOTELARIAS | D9: 0.1
A10: =B10&"-"&C10 -> MODERADO-PAPEL | B10: MODERADO | C10: PAPEL | D10: 0.32
A11: =B11&"-"&C11 -> MODERADO-TIJOLO | B11: MODERADO | C11: TIJOLO | D11: 0.35
A12: =B12&"-"&C12 -> MODERADO-HIBRIDOS | B12: MODERADO | C12: HIBRIDOS | D12: 0.08
A13: =B13&"-"&C13 -> MODERADO-FOFs | B13: MODERADO | C13: FOFs | D13: 0.05
A14: =B14&"-"&C14 -> MODERADO-DESENVOLVIMENTO | B14: MODERADO | C14: DESENVOLVIMENTO | D14: 0.1
A15: =B15&"-"&C15 -> MODERADO-HOTELARIAS | B15: MODERADO | C15: HOTELARIAS | D15: 0.1
... A21: =B21&"-"&C21 -> CONSERVADOR-HOTELARIAS | B21: CONSERVADOR | C21: HOTELARIAS | D21: 0
